{"medianCorrelation": 0.35429219170925713, "thirdQuartileKurtosis": -0.36981513684793654, "logNumberOfFeatures": 1.6094379124341003, "meanSkewness": 0.06670006370911358, "thirdQuartileSkewness": 0.3164904970700513, "medianCovariance": 0.5169038031319911, "maxCovariance": 3.1131794183445187, "medianKurtosis": -0.9544067965280811, "maxCorrelation": 0.9627570970509663, "firstQuartileCovariance": -0.058946644295301984, "medianSkewness": 0.10390469611738928, "thirdQuartileCorrelation": 0.8717541573048718, "logDatasetRatio": -3.4011973816621555, "dataset": "iris.csv", "firstQuartileSkewness": -0.14588573724354842, "thirdQuartileCovariance": 1.2736823266219246, "PCASkewnessFirstPC": -0.21656138749998327, "maxSkewness": 0.3307028127733152, "minKurtosis": -1.3953593021397128, "meanCorrelation": 0.2943392419598988, "logNumberOfInstances": 5.0106352940962555, "numberOfMissingValues": 0, "minSkewness": -0.2717119501716395, "numberOfInstances": 150.0, "missingValuesRatio": 0.0, "trajectory": [[{"random_state___TSNE": 0, "n_clusters___KMeans": 5, "early_exaggeration___TSNE": 12.0, "clustering_choice": "KMeans", "n_components___TSNE": 2, "dim_reduction_choice": "TSNE", "perplexity___TSNE": 30.0}, 2147483648], [{"random_state___TSNE": 0, "n_clusters___KMeans": 5, "early_exaggeration___TSNE": 12.0, "clustering_choice": "KMeans", "n_components___TSNE": 2, "dim_reduction_choice": "TSNE", "perplexity___TSNE": 30.0}, -0.4980872571468353], [{"n_components___GaussianMixture": 4, "warm_start___GaussianMixture": true, "random_state___TSNE": 0, "covariance_type___GaussianMixture": "diag", "early_exaggeration___TSNE": 11.11264171350707, "clustering_choice": "GaussianMixture", "n_components___TSNE": 2, "init_params___GaussianMixture": "kmeans", "dim_reduction_choice": "TSNE", "random_state___GaussianMixture": 1, "perplexity___TSNE": 45.64223540157838}, -0.605009138584137], [{"n_components___GaussianMixture": 2, "warm_start___GaussianMixture": false, "random_state___TSNE": 0, "covariance_type___GaussianMixture": "tied", "early_exaggeration___TSNE": 11.55930725455022, "clustering_choice": "GaussianMixture", "n_components___TSNE": 2, "init_params___GaussianMixture": "kmeans", "dim_reduction_choice": "TSNE", "random_state___GaussianMixture": 1, "perplexity___TSNE": 38.66479875852276}, -0.8572989106178284]], "PCAKurtosisFirstPC": -1.3710394359491644, "PCAFractionOfComponentsFor95PercentVariance": 0.5, "sparsity": 0.0, "minCovariance": -0.32171275167785235, "datasetRatio": 0.03333333333333333, "numberOfFeatures": 5.0, "isMissingValues": false, "firstQuartileKurtosis": -1.3502740586333175, "meanCovariance": 0.6115821029082775, "minCorrelation": -0.42051609640115445, "firstQuartileCorrelation": -0.35654408961380535, "meanKurtosis": -0.7656823989531729, "sparsityOnNumericColumns": 0.0, "maxKurtosis": 0.24144329938318343, "runhistory": [[{"early_exaggeration___TSNE": 11.55930725455022, "covariance_type___GaussianMixture": "tied", "n_components___GaussianMixture": 2, "clustering_choice": "GaussianMixture", "random_state___GaussianMixture": 1, "init_params___GaussianMixture": "kmeans", "n_components___TSNE": 2, "dim_reduction_choice": "TSNE", "perplexity___TSNE": 38.66479875852276}, -0.8572989106178284], [{"early_exaggeration___TSNE": 12.746295939187124, "n_clusters___Birch": 2, "branching_factor___Birch": 154, "random_state___TSNE": 7, "clustering_choice": "Birch", "n_components___TSNE": 2, "dim_reduction_choice": "TSNE", "perplexity___TSNE": 46.85649989272273}, -0.8336592316627502], [{"n_clusters___KMeans": 3, "early_exaggeration___TSNE": 12.214655138851665, "clustering_choice": "KMeans", "n_components___TSNE": 2, "dim_reduction_choice": "TSNE", "perplexity___TSNE": 32.476677851031695}, -0.6505547165870667], [{"n_clusters___KMeans": 4, "early_exaggeration___TSNE": 12.72056970904, "clustering_choice": "KMeans", "n_components___TSNE": 2, "dim_reduction_choice": "TSNE", "perplexity___TSNE": 38.44658872925447}, -0.6190556287765503], [{"early_exaggeration___TSNE": 11.561240698130181, "n_clusters___KMeans": 3, "random_state___TSNE": 2, "clustering_choice": "KMeans", "n_components___TSNE": 2, "dim_reduction_choice": "TSNE", "perplexity___TSNE": 66.3049370523731}, -0.6115514039993286], [{"n_clusters___KMeans": 4, "early_exaggeration___TSNE": 14.173151724145326, "clustering_choice": "KMeans", "n_components___TSNE": 2, "dim_reduction_choice": "TSNE", "perplexity___TSNE": 43.48529107903216}, -0.607230544090271], [{"early_exaggeration___TSNE": 11.11264171350707, "covariance_type___GaussianMixture": "diag", "n_components___GaussianMixture": 4, "clustering_choice": "GaussianMixture", "random_state___GaussianMixture": 1, "init_params___GaussianMixture": "kmeans", "n_components___TSNE": 2, "warm_start___GaussianMixture": true, "dim_reduction_choice": "TSNE", "perplexity___TSNE": 45.64223540157838}, -0.605009138584137], [{"n_clusters___KMeans": 4, "early_exaggeration___TSNE": 13.69281998849403, "clustering_choice": "KMeans", "n_components___TSNE": 2, "dim_reduction_choice": "TSNE", "perplexity___TSNE": 40.66523403544935}, -0.6007277369499207], [{"n_clusters___KMeans": 1, "n_components___TruncatedSVD": 7, "algorithm___TruncatedSVD": "arpack", "clustering_choice": "KMeans", "dim_reduction_choice": "TruncatedSVD", "random_state___TruncatedSVD": 2}, -0.6005048751831055], [{"n_clusters___KMeans": 4, "early_exaggeration___TSNE": 12.761446146738663, "clustering_choice": "KMeans", "n_components___TSNE": 2, "dim_reduction_choice": "TSNE", "perplexity___TSNE": 38.11774886332608}, -0.5964855551719666], [{"early_exaggeration___TSNE": 12.227576864985366, "n_clusters___Birch": 4, "branching_factor___Birch": 221, "random_state___TSNE": 2, "clustering_choice": "Birch", "n_components___TSNE": 2, "dim_reduction_choice": "TSNE", "perplexity___TSNE": 45.76871259907787}, -0.5958915948867798], [{"early_exaggeration___TSNE": 12.214655138851665, "n_clusters___KMeans": 4, "random_state___TSNE": 2, "clustering_choice": "KMeans", "n_components___TSNE": 2, "dim_reduction_choice": "TSNE", "perplexity___TSNE": 48.95267930661911}, -0.5874927043914795], [{"early_exaggeration___TSNE": 12.236771696217055, "n_clusters___Birch": 4, "branching_factor___Birch": 140, "random_state___TSNE": 4, "clustering_choice": "Birch", "n_components___TSNE": 2, "dim_reduction_choice": "TSNE", "perplexity___TSNE": 43.677317845379015}, -0.5847129225730896], [{"early_exaggeration___TSNE": 13.036113822910131, "n_clusters___Birch": 18, "branching_factor___Birch": 74, "random_state___TSNE": 3, "clustering_choice": "Birch", "n_components___TSNE": 2, "dim_reduction_choice": "TSNE", "perplexity___TSNE": 139.94806094714332}, -0.5820196270942688], [{"early_exaggeration___TSNE": 12.83992060062565, "n_clusters___KMeans": 4, "random_state___TSNE": 2, "clustering_choice": "KMeans", "n_components___TSNE": 2, "dim_reduction_choice": "TSNE", "perplexity___TSNE": 48.95267930661911}, -0.5816382765769958], [{"n_components___TruncatedSVD": 8, "algorithm___TruncatedSVD": "arpack", "covariance_type___GaussianMixture": "diag", "n_components___GaussianMixture": 29, "clustering_choice": "GaussianMixture", "random_state___GaussianMixture": 8, "init_params___GaussianMixture": "random", "dim_reduction_choice": "TruncatedSVD", "random_state___TruncatedSVD": 5}, -0.5718336701393127], [{"bin_seeding___MeanShift": true, "bandwidth___MeanShift": 15.823098677776764, "algorithm___TruncatedSVD": "randomized", "clustering_choice": "MeanShift", "dim_reduction_choice": "TruncatedSVD", "n_components___TruncatedSVD": 6, "random_state___TruncatedSVD": 8}, -0.5716314280485179], [{"random_state___TSNE": 5, "early_exaggeration___TSNE": 15.444331842575274, "covariance_type___GaussianMixture": "diag", "n_components___GaussianMixture": 22, "clustering_choice": "GaussianMixture", "random_state___GaussianMixture": 3, "init_params___GaussianMixture": "random", "n_components___TSNE": 2, "warm_start___GaussianMixture": true, "dim_reduction_choice": "TSNE", "perplexity___TSNE": 33.636418969736994}, -0.55682772397995], [{"random_state___KernelPCA": 4, "n_clusters___Birch": 8, "n_components___KernelPCA": 4, "branching_factor___Birch": 929, "clustering_choice": "Birch", "kernel___KernelPCA": "poly", "dim_reduction_choice": "KernelPCA"}, -0.5124089184668872], [{"n_clusters___KMeans": 27, "n_components___TruncatedSVD": 6, "algorithm___TruncatedSVD": "arpack", "clustering_choice": "KMeans", "dim_reduction_choice": "TruncatedSVD", "random_state___TruncatedSVD": 2}, -0.5040382742881775], [{"early_exaggeration___TSNE": 13.160939497250274, "covariance_type___GaussianMixture": "tied", "n_components___GaussianMixture": 6, "clustering_choice": "GaussianMixture", "init_params___GaussianMixture": "kmeans", "n_components___TSNE": 2, "warm_start___GaussianMixture": true, "dim_reduction_choice": "TSNE", "perplexity___TSNE": 43.57823535866105}, -0.5023306012153625], [{"n_clusters___KMeans": 5, "early_exaggeration___TSNE": 12.0, "clustering_choice": "KMeans", "n_components___TSNE": 2, "dim_reduction_choice": "TSNE", "perplexity___TSNE": 30.0}, -0.4980872571468353], [{"eigen_solver___SpectralClustering": "arpack", "n_clusters___SpectralClustering": 7, "random_state___TSNE": 6, "assign_labels___SpectralClustering": "kmeans", "early_exaggeration___TSNE": 6.601193403412915, "clustering_choice": "SpectralClustering", "n_components___TSNE": 2, "affinity___SpectralClustering": "nearest_neighbors", "dim_reduction_choice": "TSNE", "perplexity___TSNE": 280.17587403227304}, -0.489681601524353], [{"batch_size___IncrementalPCA": 964, "n_clusters___SpectralClustering": 2, "assign_labels___SpectralClustering": "kmeans", "eigen_solver___SpectralClustering": "arpack", "clustering_choice": "SpectralClustering", "n_components___IncrementalPCA": 2, "dim_reduction_choice": "IncrementalPCA", "whiten___IncrementalPCA": true, "affinity___SpectralClustering": "laplacian"}, -0.4869860991732247], [{"early_exaggeration___TSNE": 11.805440657544912, "affinity___AffinityPropagation": "euclidean", "random_state___TSNE": 1, "clustering_choice": "AffinityPropagation", "n_components___TSNE": 2, "damping___AffinityPropagation": 0.5866320982609904, "dim_reduction_choice": "TSNE", "perplexity___TSNE": 26.090653870722104}, -0.4695076048374176], [{"random_state___TSNE": 4, "early_exaggeration___TSNE": 13.901266623242623, "covariance_type___GaussianMixture": "tied", "n_components___GaussianMixture": 5, "clustering_choice": "GaussianMixture", "init_params___GaussianMixture": "kmeans", "n_components___TSNE": 2, "dim_reduction_choice": "TSNE", "perplexity___TSNE": 41.84078177267627}, -0.465347021818161], [{"random_state___KernelPCA": 9, "n_components___KernelPCA": 2, "covariance_type___GaussianMixture": "spherical", "n_components___GaussianMixture": 10, "clustering_choice": "GaussianMixture", "random_state___GaussianMixture": 1, "init_params___GaussianMixture": "kmeans", "kernel___KernelPCA": "rbf", "dim_reduction_choice": "KernelPCA"}, -0.4631208247241059], [{"n_components___KernelPCA": 3, "clustering_choice": "KMeans", "n_clusters___KMeans": 16, "kernel___KernelPCA": "poly", "dim_reduction_choice": "KernelPCA"}, -0.4596280130278572], [{"eigen_solver___SpectralClustering": "arpack", "n_clusters___SpectralClustering": 9, "assign_labels___SpectralClustering": "kmeans", "early_exaggeration___TSNE": 11.587650067766514, "clustering_choice": "SpectralClustering", "n_components___TSNE": 2, "affinity___SpectralClustering": "rbf", "dim_reduction_choice": "TSNE", "perplexity___TSNE": 36.288024337949224}, -0.45903369784355164], [{"random_state___KernelPCA": 8, "n_clusters___KMeans": 3, "clustering_choice": "KMeans", "n_components___KernelPCA": 6, "kernel___KernelPCA": "linear", "dim_reduction_choice": "KernelPCA"}, -0.45897178669792205], [{"eigen_solver___SpectralClustering": "arpack", "n_clusters___SpectralClustering": 6, "random_state___TSNE": 2, "assign_labels___SpectralClustering": "kmeans", "early_exaggeration___TSNE": 12.165329892916542, "clustering_choice": "SpectralClustering", "n_components___TSNE": 2, "affinity___SpectralClustering": "poly", "dim_reduction_choice": "TSNE", "perplexity___TSNE": 41.196038385293775}, -0.45830652117729187], [{"random_state___TSNE": 3, "early_exaggeration___TSNE": 12.156973378330779, "covariance_type___GaussianMixture": "tied", "n_components___GaussianMixture": 9, "clustering_choice": "GaussianMixture", "random_state___GaussianMixture": 5, "init_params___GaussianMixture": "kmeans", "n_components___TSNE": 2, "warm_start___GaussianMixture": true, "dim_reduction_choice": "TSNE", "perplexity___TSNE": 37.55988297283223}, -0.4553104043006897], [{"whiten___FastICA": true, "random_state___FastICA": 8, "n_components___FastICA": 2, "fun___FastICA": "cube", "clustering_choice": "MiniBatchKMeans", "batch_size___MiniBatchKMeans": 597, "n_clusters___MiniBatchKMeans": 9, "dim_reduction_choice": "FastICA", "algorithm___FastICA": "deflation", "random_state___MiniBatchKMeans": 4}, -0.4532866675907103], [{"whiten___PCA": true, "n_components___PCA": 2, "affinity___AffinityPropagation": "euclidean", "clustering_choice": "AffinityPropagation", "random_state___PCA": 6, "dim_reduction_choice": "PCA", "damping___AffinityPropagation": 0.7824804280863398, "svd_solver___PCA": "arpack"}, -0.4522847659189002], [{"whiten___PCA": true, "n_components___PCA": 2, "affinity___AffinityPropagation": "euclidean", "clustering_choice": "AffinityPropagation", "random_state___PCA": 3, "dim_reduction_choice": "PCA", "damping___AffinityPropagation": 0.6703581914182102, "svd_solver___PCA": "auto"}, -0.4522847659189], [{"n_components___FastICA": 2, "fun___FastICA": "logcosh", "affinity___AffinityPropagation": "euclidean", "clustering_choice": "AffinityPropagation", "dim_reduction_choice": "FastICA", "damping___AffinityPropagation": 0.886352537096536, "algorithm___FastICA": "parallel"}, -0.4522847659189], [{"early_exaggeration___TSNE": 13.059051709842349, "n_clusters___KMeans": 9, "random_state___TSNE": 3, "clustering_choice": "KMeans", "n_components___TSNE": 2, "dim_reduction_choice": "TSNE", "perplexity___TSNE": 132.78229340124705}, -0.44850218296051025], [{"n_components___PCA": 2, "n_clusters___KMeans": 13, "clustering_choice": "KMeans", "random_state___PCA": 3, "dim_reduction_choice": "PCA", "svd_solver___PCA": "arpack"}, -0.4477006879976227], [{"batch_size___IncrementalPCA": 348, "affinity___AffinityPropagation": "euclidean", "n_components___IncrementalPCA": 2, "clustering_choice": "AffinityPropagation", "dim_reduction_choice": "IncrementalPCA", "damping___AffinityPropagation": 0.969260151574079}, -0.4474258453708838], [{"early_exaggeration___TSNE": 12.056015353093596, "n_clusters___KMeans": 5, "random_state___TSNE": 1, "clustering_choice": "KMeans", "n_components___TSNE": 2, "dim_reduction_choice": "TSNE", "perplexity___TSNE": 67.25272585660042}, -0.4469931125640869], [{"early_exaggeration___TSNE": 12.100174681818228, "n_clusters___KMeans": 5, "random_state___TSNE": 2, "clustering_choice": "KMeans", "n_components___TSNE": 2, "dim_reduction_choice": "TSNE", "perplexity___TSNE": 66.89974908784453}, -0.4462277293205261], [{"batch_size___MiniBatchKMeans": 285, "random_state___MiniBatchKMeans": 1, "clustering_choice": "MiniBatchKMeans", "early_exaggeration___TSNE": 10.896269093689085, "n_clusters___MiniBatchKMeans": 12, "n_components___TSNE": 2, "dim_reduction_choice": "TSNE", "perplexity___TSNE": 38.3652978687497}, -0.4423011839389801], [{"early_exaggeration___TSNE": 11.686279910633079, "covariance_type___GaussianMixture": "spherical", "n_components___GaussianMixture": 8, "clustering_choice": "GaussianMixture", "init_params___GaussianMixture": "kmeans", "n_components___TSNE": 2, "dim_reduction_choice": "TSNE", "perplexity___TSNE": 37.717098906315854}, -0.44139575958251953], [{"batch_size___IncrementalPCA": 911, "whiten___IncrementalPCA": true, "init_params___GaussianMixture": "kmeans", "covariance_type___GaussianMixture": "tied", "n_components___GaussianMixture": 11, "clustering_choice": "GaussianMixture", "random_state___GaussianMixture": 2, "n_components___IncrementalPCA": 2, "dim_reduction_choice": "IncrementalPCA", "warm_start___GaussianMixture": true}, -0.44085603762197706], [{"n_components___PCA": 2, "clustering_choice": "MiniBatchKMeans", "batch_size___MiniBatchKMeans": 333, "n_clusters___MiniBatchKMeans": 9, "random_state___PCA": 4, "dim_reduction_choice": "PCA", "random_state___MiniBatchKMeans": 3, "svd_solver___PCA": "randomized"}, -0.43974867926937883], [{"random_state___KernelPCA": 1, "n_components___KernelPCA": 3, "min_samples___OPTICS": 554, "cluster_method___OPTICS": "dbscan", "clustering_choice": "OPTICS", "metric___OPTICS": "l1", "kernel___KernelPCA": "linear", "dim_reduction_choice": "KernelPCA"}, -0.4384556487952673], [{"early_exaggeration___TSNE": 11.122568527223285, "n_clusters___Birch": 5, "branching_factor___Birch": 129, "random_state___TSNE": 2, "clustering_choice": "Birch", "n_components___TSNE": 2, "dim_reduction_choice": "TSNE", "perplexity___TSNE": 69.48376691828962}, -0.4383389353752136], [{"early_exaggeration___TSNE": 12.511602866463736, "covariance_type___GaussianMixture": "tied", "n_components___GaussianMixture": 17, "clustering_choice": "GaussianMixture", "random_state___GaussianMixture": 1, "init_params___GaussianMixture": "kmeans", "n_components___TSNE": 2, "warm_start___GaussianMixture": true, "dim_reduction_choice": "TSNE", "perplexity___TSNE": 62.114760129037016}, -0.4381386339664459], [{"clustering_choice": "KMeans", "algorithm___TruncatedSVD": "arpack", "n_clusters___KMeans": 12, "n_components___TruncatedSVD": 2, "dim_reduction_choice": "TruncatedSVD"}, -0.43648228981109827], [{"random_state___TSNE": 2, "early_exaggeration___TSNE": 14.698185371122712, "covariance_type___GaussianMixture": "tied", "n_components___GaussianMixture": 6, "clustering_choice": "GaussianMixture", "random_state___GaussianMixture": 1, "init_params___GaussianMixture": "kmeans", "n_components___TSNE": 2, "dim_reduction_choice": "TSNE", "perplexity___TSNE": 37.85248922190014}, -0.4359585642814636], [{"early_exaggeration___TSNE": 10.960434400024434, "n_clusters___KMeans": 19, "random_state___TSNE": 3, "clustering_choice": "KMeans", "n_components___TSNE": 2, "dim_reduction_choice": "TSNE", "perplexity___TSNE": 49.39453703924507}, -0.43485787510871887], [{"bandwidth___MeanShift": 39.7062473814413, "algorithm___TruncatedSVD": "arpack", "clustering_choice": "MeanShift", "dim_reduction_choice": "TruncatedSVD", "n_components___TruncatedSVD": 4, "random_state___TruncatedSVD": 9}, -0.4347390830516815], [{"affinity___AgglomerativeClustering": "cityblock", "early_exaggeration___TSNE": 7.22863885104359, "linkage___AgglomerativeClustering": "average", "random_state___TSNE": 3, "clustering_choice": "AgglomerativeClustering", "n_clusters___AgglomerativeClustering": 17, "dim_reduction_choice": "TSNE", "n_components___TSNE": 2, "perplexity___TSNE": 133.30286385933164}, -0.4336213767528534], [{"affinity___AgglomerativeClustering": "l2", "linkage___AgglomerativeClustering": "complete", "early_exaggeration___TSNE": 5.25848116642942, "clustering_choice": "AgglomerativeClustering", "n_clusters___AgglomerativeClustering": 18, "dim_reduction_choice": "TSNE", "n_components___TSNE": 2, "perplexity___TSNE": 252.54583529514983}, -0.43328848481178284], [{"eigen_solver___SpectralClustering": "arpack", "n_clusters___SpectralClustering": 8, "assign_labels___SpectralClustering": "kmeans", "early_exaggeration___TSNE": 11.473543377905045, "clustering_choice": "SpectralClustering", "n_components___TSNE": 2, "affinity___SpectralClustering": "laplacian", "dim_reduction_choice": "TSNE", "perplexity___TSNE": 50.9543516340971}, -0.43294239044189453], [{"eigen_solver___SpectralClustering": "arpack", "n_clusters___SpectralClustering": 7, "assign_labels___SpectralClustering": "discretize", "early_exaggeration___TSNE": 12.129437145798878, "clustering_choice": "SpectralClustering", "n_components___TSNE": 2, "affinity___SpectralClustering": "laplacian", "dim_reduction_choice": "TSNE", "perplexity___TSNE": 35.53541062679964}, -0.4324992001056671], [{"early_exaggeration___TSNE": 11.31375508464173, "n_clusters___Birch": 11, "branching_factor___Birch": 279, "random_state___TSNE": 1, "clustering_choice": "Birch", "n_components___TSNE": 2, "dim_reduction_choice": "TSNE", "perplexity___TSNE": 76.50598573209085}, -0.4314950704574585], [{"batch_size___IncrementalPCA": 495, "whiten___IncrementalPCA": true, "n_clusters___MiniBatchKMeans": 13, "batch_size___MiniBatchKMeans": 516, "clustering_choice": "MiniBatchKMeans", "n_components___IncrementalPCA": 2, "dim_reduction_choice": "IncrementalPCA", "random_state___MiniBatchKMeans": 3}, -0.4304797109127398], [{"n_clusters___KMeans": 4, "n_components___TruncatedSVD": 4, "algorithm___TruncatedSVD": "randomized", "clustering_choice": "KMeans", "dim_reduction_choice": "TruncatedSVD", "random_state___TruncatedSVD": 5}, -0.4245357423713918], [{"random_state___KernelPCA": 7, "n_components___KernelPCA": 7, "min_samples___OPTICS": 788, "cluster_method___OPTICS": "xi", "clustering_choice": "OPTICS", "metric___OPTICS": "minkowski", "kernel___KernelPCA": "poly", "dim_reduction_choice": "KernelPCA"}, -0.4244685690043303], [{"n_components___PCA": 2, "clustering_choice": "MiniBatchKMeans", "batch_size___MiniBatchKMeans": 850, "n_clusters___MiniBatchKMeans": 5, "random_state___PCA": 6, "dim_reduction_choice": "PCA", "random_state___MiniBatchKMeans": 8, "svd_solver___PCA": "randomized"}, -0.4243763751493632], [{"n_components___PCA": 2, "n_clusters___KMeans": 5, "clustering_choice": "KMeans", "random_state___PCA": 1, "dim_reduction_choice": "PCA", "svd_solver___PCA": "arpack"}, -0.4231051983988884], [{"eigen_solver___SpectralClustering": "arpack", "n_components___PCA": 2, "svd_solver___PCA": "auto", "assign_labels___SpectralClustering": "kmeans", "clustering_choice": "SpectralClustering", "random_state___PCA": 2, "dim_reduction_choice": "PCA", "n_clusters___SpectralClustering": 10, "affinity___SpectralClustering": "laplacian"}, -0.4200453514813201], [{"affinity___AgglomerativeClustering": "cityblock", "early_exaggeration___TSNE": 15.131646574893796, "linkage___AgglomerativeClustering": "complete", "random_state___TSNE": 3, "clustering_choice": "AgglomerativeClustering", "n_clusters___AgglomerativeClustering": 9, "dim_reduction_choice": "TSNE", "n_components___TSNE": 2, "perplexity___TSNE": 43.10035641096222}, -0.41950905323028564], [{"n_clusters___KMeans": 5, "n_components___TruncatedSVD": 2, "algorithm___TruncatedSVD": "randomized", "clustering_choice": "KMeans", "dim_reduction_choice": "TruncatedSVD", "random_state___TruncatedSVD": 1}, -0.4181810596653058], [{"random_state___TruncatedSVD": 5, "algorithm___TruncatedSVD": "arpack", "clustering_choice": "MiniBatchKMeans", "batch_size___MiniBatchKMeans": 871, "n_clusters___MiniBatchKMeans": 2, "dim_reduction_choice": "TruncatedSVD", "n_components___TruncatedSVD": 5, "random_state___MiniBatchKMeans": 5}, -0.41771790385246277], [{"affinity___AgglomerativeClustering": "euclidean", "n_components___PCA": 2, "linkage___AgglomerativeClustering": "average", "clustering_choice": "AgglomerativeClustering", "n_clusters___AgglomerativeClustering": 11, "random_state___PCA": 4, "dim_reduction_choice": "PCA", "svd_solver___PCA": "full"}, -0.41738147517344437], [{"random_state___TruncatedSVD": 4, "algorithm___TruncatedSVD": "arpack", "clustering_choice": "MiniBatchKMeans", "batch_size___MiniBatchKMeans": 756, "n_clusters___MiniBatchKMeans": 11, "dim_reduction_choice": "TruncatedSVD", "n_components___TruncatedSVD": 2, "random_state___MiniBatchKMeans": 1}, -0.41507113061815715], [{"early_exaggeration___TSNE": 12.881504826447873, "covariance_type___GaussianMixture": "tied", "n_components___GaussianMixture": 9, "clustering_choice": "GaussianMixture", "random_state___GaussianMixture": 4, "init_params___GaussianMixture": "kmeans", "n_components___TSNE": 2, "warm_start___GaussianMixture": true, "dim_reduction_choice": "TSNE", "perplexity___TSNE": 43.57823535866105}, -0.41492852568626404], [{"random_state___KernelPCA": 2, "n_clusters___KMeans": 26, "clustering_choice": "KMeans", "n_components___KernelPCA": 2, "kernel___KernelPCA": "poly", "dim_reduction_choice": "KernelPCA"}, -0.41389259070909096], [{"early_exaggeration___TSNE": 5.5978818329576345, "n_clusters___Birch": 9, "branching_factor___Birch": 155, "random_state___TSNE": 2, "clustering_choice": "Birch", "n_components___TSNE": 2, "dim_reduction_choice": "TSNE", "perplexity___TSNE": 65.39395956950945}, -0.41386377811431885], [{"random_state___TruncatedSVD": 8, "algorithm___TruncatedSVD": "randomized", "clustering_choice": "MiniBatchKMeans", "batch_size___MiniBatchKMeans": 347, "n_clusters___MiniBatchKMeans": 11, "dim_reduction_choice": "TruncatedSVD", "n_components___TruncatedSVD": 2, "random_state___MiniBatchKMeans": 1}, -0.4137477071440619], [{"eigen_solver___SpectralClustering": "arpack", "n_clusters___SpectralClustering": 10, "random_state___TSNE": 8, "assign_labels___SpectralClustering": "discretize", "early_exaggeration___TSNE": 14.620388525380319, "clustering_choice": "SpectralClustering", "n_components___TSNE": 2, "affinity___SpectralClustering": "rbf", "dim_reduction_choice": "TSNE", "perplexity___TSNE": 98.62579078762174}, -0.41312113404273987], [{"batch_size___IncrementalPCA": 557, "whiten___IncrementalPCA": true, "init_params___GaussianMixture": "kmeans", "covariance_type___GaussianMixture": "tied", "n_components___GaussianMixture": 22, "clustering_choice": "GaussianMixture", "n_components___IncrementalPCA": 2, "dim_reduction_choice": "IncrementalPCA", "warm_start___GaussianMixture": true}, -0.41221243934020807], [{"random_state___TruncatedSVD": 5, "algorithm___TruncatedSVD": "randomized", "clustering_choice": "MiniBatchKMeans", "batch_size___MiniBatchKMeans": 108, "n_clusters___MiniBatchKMeans": 11, "dim_reduction_choice": "TruncatedSVD", "n_components___TruncatedSVD": 2, "random_state___MiniBatchKMeans": 2}, -0.4118944723874499], [{"n_components___PCA": 2, "n_clusters___Birch": 22, "branching_factor___Birch": 34, "clustering_choice": "Birch", "random_state___PCA": 2, "dim_reduction_choice": "PCA", "svd_solver___PCA": "arpack"}, -0.4086347382726866], [{"n_components___PCA": 2, "n_clusters___Birch": 19, "branching_factor___Birch": 314, "clustering_choice": "Birch", "random_state___PCA": 5, "dim_reduction_choice": "PCA", "svd_solver___PCA": "full"}, -0.40863473822480684], [{"n_components___PCA": 2, "n_clusters___Birch": 25, "branching_factor___Birch": 584, "clustering_choice": "Birch", "random_state___PCA": 8, "dim_reduction_choice": "PCA", "svd_solver___PCA": "arpack"}, -0.4086347382248068], [{"eigen_solver___SpectralClustering": "arpack", "n_clusters___SpectralClustering": 16, "assign_labels___SpectralClustering": "kmeans", "clustering_choice": "SpectralClustering", "random_state___KernelPCA": 1, "n_components___KernelPCA": 6, "kernel___KernelPCA": "rbf", "affinity___SpectralClustering": "poly", "dim_reduction_choice": "KernelPCA"}, -0.4074954850710908], [{"random_state___TSNE": 1, "random_state___MiniBatchKMeans": 2, "n_clusters___MiniBatchKMeans": 12, "early_exaggeration___TSNE": 11.537191504081516, "clustering_choice": "MiniBatchKMeans", "batch_size___MiniBatchKMeans": 100, "n_components___TSNE": 2, "dim_reduction_choice": "TSNE", "perplexity___TSNE": 193.25090149588095}, -0.40486767888069153], [{"random_state___TruncatedSVD": 5, "algorithm___TruncatedSVD": "randomized", "clustering_choice": "MiniBatchKMeans", "batch_size___MiniBatchKMeans": 492, "n_clusters___MiniBatchKMeans": 10, "dim_reduction_choice": "TruncatedSVD", "n_components___TruncatedSVD": 2, "random_state___MiniBatchKMeans": 4}, -0.40404761352626795], [{"random_state___KernelPCA": 6, "n_components___KernelPCA": 3, "min_samples___OPTICS": 791, "cluster_method___OPTICS": "dbscan", "clustering_choice": "OPTICS", "metric___OPTICS": "euclidean", "kernel___KernelPCA": "poly", "dim_reduction_choice": "KernelPCA"}, -0.40364768058371736], [{"n_components___TruncatedSVD": 2, "algorithm___TruncatedSVD": "randomized", "covariance_type___GaussianMixture": "tied", "n_components___GaussianMixture": 8, "clustering_choice": "GaussianMixture", "init_params___GaussianMixture": "kmeans", "dim_reduction_choice": "TruncatedSVD", "warm_start___GaussianMixture": true, "random_state___TruncatedSVD": 3}, -0.40323751011598796], [{"random_state___TSNE": 2, "early_exaggeration___TSNE": 12.0, "covariance_type___GaussianMixture": "tied", "n_components___GaussianMixture": 18, "clustering_choice": "GaussianMixture", "random_state___GaussianMixture": 7, "init_params___GaussianMixture": "kmeans", "n_components___TSNE": 2, "warm_start___GaussianMixture": true, "dim_reduction_choice": "TSNE", "perplexity___TSNE": 33.87254142468821}, -0.4027395248413086], [{"eigen_solver___SpectralClustering": "arpack", "n_clusters___SpectralClustering": 11, "random_state___TSNE": 2, "assign_labels___SpectralClustering": "discretize", "early_exaggeration___TSNE": 12.192762349893545, "clustering_choice": "SpectralClustering", "n_components___TSNE": 2, "affinity___SpectralClustering": "nearest_neighbors", "dim_reduction_choice": "TSNE", "perplexity___TSNE": 53.80298609692362}, -0.4003581702709198], [{"n_clusters___KMeans": 4, "n_components___TruncatedSVD": 3, "algorithm___TruncatedSVD": "randomized", "clustering_choice": "KMeans", "dim_reduction_choice": "TruncatedSVD", "random_state___TruncatedSVD": 2}, -0.39760573666103743], [{"n_components___TruncatedSVD": 2, "algorithm___TruncatedSVD": "randomized", "covariance_type___GaussianMixture": "full", "n_components___GaussianMixture": 10, "clustering_choice": "GaussianMixture", "init_params___GaussianMixture": "kmeans", "dim_reduction_choice": "TruncatedSVD", "warm_start___GaussianMixture": true, "random_state___TruncatedSVD": 6}, -0.3968402674993333], [{"n_components___TruncatedSVD": 6, "algorithm___TruncatedSVD": "arpack", "covariance_type___GaussianMixture": "tied", "n_components___GaussianMixture": 17, "clustering_choice": "GaussianMixture", "random_state___GaussianMixture": 2, "init_params___GaussianMixture": "kmeans", "dim_reduction_choice": "TruncatedSVD", "random_state___TruncatedSVD": 8}, -0.39637490913780193], [{"batch_size___IncrementalPCA": 250, "whiten___IncrementalPCA": true, "n_clusters___MiniBatchKMeans": 7, "batch_size___MiniBatchKMeans": 359, "clustering_choice": "MiniBatchKMeans", "n_components___IncrementalPCA": 2, "dim_reduction_choice": "IncrementalPCA", "random_state___MiniBatchKMeans": 1}, -0.3960583388921757], [{"algorithm___FastICA": "parallel", "eigen_solver___SpectralClustering": "arpack", "n_clusters___SpectralClustering": 10, "fun___FastICA": "cube", "assign_labels___SpectralClustering": "kmeans", "clustering_choice": "SpectralClustering", "dim_reduction_choice": "FastICA", "n_components___FastICA": 2, "random_state___FastICA": 3, "affinity___SpectralClustering": "laplacian"}, -0.3913095547473619], [{"random_state___KernelPCA": 3, "n_clusters___KMeans": 6, "clustering_choice": "KMeans", "n_components___KernelPCA": 8, "kernel___KernelPCA": "cosine", "dim_reduction_choice": "KernelPCA"}, -0.39083131453362624], [{"early_exaggeration___TSNE": 11.478122369589876, "covariance_type___GaussianMixture": "diag", "n_components___GaussianMixture": 6, "clustering_choice": "GaussianMixture", "init_params___GaussianMixture": "kmeans", "n_components___TSNE": 2, "warm_start___GaussianMixture": true, "dim_reduction_choice": "TSNE", "perplexity___TSNE": 62.10781831387286}, -0.39007213711738586], [{"n_clusters___KMeans": 23, "n_components___TruncatedSVD": 2, "algorithm___TruncatedSVD": "randomized", "clustering_choice": "KMeans", "dim_reduction_choice": "TruncatedSVD", "random_state___TruncatedSVD": 7}, -0.38956941673994816], [{"n_components___PCA": 2, "init_params___GaussianMixture": "kmeans", "covariance_type___GaussianMixture": "spherical", "n_components___GaussianMixture": 18, "clustering_choice": "GaussianMixture", "random_state___GaussianMixture": 6, "random_state___PCA": 9, "dim_reduction_choice": "PCA", "warm_start___GaussianMixture": true, "svd_solver___PCA": "auto"}, -0.38357406882796513], [{"n_clusters___Birch": 10, "branching_factor___Birch": 372, "algorithm___TruncatedSVD": "arpack", "clustering_choice": "Birch", "dim_reduction_choice": "TruncatedSVD", "n_components___TruncatedSVD": 2, "random_state___TruncatedSVD": 7}, -0.38135789822941724], [{"n_clusters___Birch": 10, "branching_factor___Birch": 607, "algorithm___TruncatedSVD": "arpack", "clustering_choice": "Birch", "dim_reduction_choice": "TruncatedSVD", "n_components___TruncatedSVD": 2, "random_state___TruncatedSVD": 8}, -0.38135789822941724], [{"batch_size___IncrementalPCA": 404, "n_clusters___SpectralClustering": 9, "assign_labels___SpectralClustering": "kmeans", "eigen_solver___SpectralClustering": "arpack", "clustering_choice": "SpectralClustering", "n_components___IncrementalPCA": 2, "dim_reduction_choice": "IncrementalPCA", "whiten___IncrementalPCA": true, "affinity___SpectralClustering": "nearest_neighbors"}, -0.37969189430077094], [{"affinity___AgglomerativeClustering": "manhattan", "algorithm___TruncatedSVD": "randomized", "linkage___AgglomerativeClustering": "average", "clustering_choice": "AgglomerativeClustering", "n_clusters___AgglomerativeClustering": 15, "dim_reduction_choice": "TruncatedSVD", "n_components___TruncatedSVD": 5, "random_state___TruncatedSVD": 7}, -0.37836108752547415], [{"n_components___TruncatedSVD": 2, "algorithm___TruncatedSVD": "arpack", "clustering_choice": "MiniBatchKMeans", "batch_size___MiniBatchKMeans": 419, "n_clusters___MiniBatchKMeans": 29, "dim_reduction_choice": "TruncatedSVD", "random_state___MiniBatchKMeans": 7}, -0.377663201026838], [{"clustering_choice": "KMeans", "n_components___PCA": 3, "n_clusters___KMeans": 15, "dim_reduction_choice": "PCA", "svd_solver___PCA": "randomized"}, -0.37085596036244456], [{"random_state___TruncatedSVD": 3, "algorithm___TruncatedSVD": "randomized", "clustering_choice": "MiniBatchKMeans", "batch_size___MiniBatchKMeans": 969, "n_clusters___MiniBatchKMeans": 19, "dim_reduction_choice": "TruncatedSVD", "n_components___TruncatedSVD": 2, "random_state___MiniBatchKMeans": 3}, -0.3664876292191992], [{"n_components___PCA": 3, "affinity___AffinityPropagation": "euclidean", "clustering_choice": "AffinityPropagation", "dim_reduction_choice": "PCA", "damping___AffinityPropagation": 0.9327906910013132, "svd_solver___PCA": "arpack"}, -0.3638001871569612], [{"n_components___PCA": 3, "affinity___AffinityPropagation": "euclidean", "clustering_choice": "AffinityPropagation", "random_state___PCA": 1, "dim_reduction_choice": "PCA", "damping___AffinityPropagation": 0.7041021240281897, "svd_solver___PCA": "arpack"}, -0.3638001871569612], [{"n_components___PCA": 3, "affinity___AffinityPropagation": "euclidean", "clustering_choice": "AffinityPropagation", "random_state___PCA": 6, "dim_reduction_choice": "PCA", "damping___AffinityPropagation": 0.7710542518328174, "svd_solver___PCA": "arpack"}, -0.3638001871569612], [{"affinity___AffinityPropagation": "euclidean", "algorithm___TruncatedSVD": "randomized", "clustering_choice": "AffinityPropagation", "n_components___TruncatedSVD": 3, "dim_reduction_choice": "TruncatedSVD", "damping___AffinityPropagation": 0.721466166598124, "random_state___TruncatedSVD": 8}, -0.36380018704983863], [{"affinity___AffinityPropagation": "euclidean", "algorithm___TruncatedSVD": "arpack", "clustering_choice": "AffinityPropagation", "n_components___TruncatedSVD": 3, "dim_reduction_choice": "TruncatedSVD", "damping___AffinityPropagation": 0.5094492704944297, "random_state___TruncatedSVD": 1}, -0.36246338804578937], [{"eigen_solver___SpectralClustering": "arpack", "n_clusters___SpectralClustering": 8, "random_state___TSNE": 5, "assign_labels___SpectralClustering": "kmeans", "early_exaggeration___TSNE": 17.544380829232274, "clustering_choice": "SpectralClustering", "n_components___TSNE": 2, "affinity___SpectralClustering": "laplacian", "dim_reduction_choice": "TSNE", "perplexity___TSNE": 290.8086544682863}, -0.3620937466621399], [{"n_components___TruncatedSVD": 3, "algorithm___TruncatedSVD": "randomized", "covariance_type___GaussianMixture": "spherical", "n_components___GaussianMixture": 11, "clustering_choice": "GaussianMixture", "init_params___GaussianMixture": "kmeans", "dim_reduction_choice": "TruncatedSVD", "warm_start___GaussianMixture": true, "random_state___TruncatedSVD": 1}, -0.35797295190361705], [{"affinity___AgglomerativeClustering": "cosine", "whiten___PCA": true, "n_components___PCA": 2, "linkage___AgglomerativeClustering": "average", "clustering_choice": "AgglomerativeClustering", "n_clusters___AgglomerativeClustering": 7, "random_state___PCA": 4, "dim_reduction_choice": "PCA", "svd_solver___PCA": "randomized"}, -0.3554160295748485], [{"batch_size___IncrementalPCA": 469, "n_clusters___MiniBatchKMeans": 25, "n_components___IncrementalPCA": 3, "batch_size___MiniBatchKMeans": 967, "clustering_choice": "MiniBatchKMeans", "dim_reduction_choice": "IncrementalPCA", "random_state___MiniBatchKMeans": 8}, -0.3492832975976969], [{"eigen_solver___SpectralClustering": "arpack", "n_clusters___SpectralClustering": 5, "assign_labels___SpectralClustering": "kmeans", "clustering_choice": "SpectralClustering", "random_state___KernelPCA": 2, "n_components___KernelPCA": 4, "kernel___KernelPCA": "linear", "affinity___SpectralClustering": "laplacian", "dim_reduction_choice": "KernelPCA"}, -0.3484987342265025], [{"affinity___AgglomerativeClustering": "euclidean", "batch_size___IncrementalPCA": 243, "linkage___AgglomerativeClustering": "ward", "n_components___IncrementalPCA": 3, "clustering_choice": "AgglomerativeClustering", "n_clusters___AgglomerativeClustering": 14, "dim_reduction_choice": "IncrementalPCA"}, -0.3457370712998294], [{"n_components___TruncatedSVD": 7, "algorithm___TruncatedSVD": "arpack", "covariance_type___GaussianMixture": "spherical", "n_components___GaussianMixture": 25, "clustering_choice": "GaussianMixture", "random_state___GaussianMixture": 5, "init_params___GaussianMixture": "random", "dim_reduction_choice": "TruncatedSVD", "warm_start___GaussianMixture": true, "random_state___TruncatedSVD": 6}, -0.34197883175138033], [{"n_clusters___KMeans": 23, "n_components___TruncatedSVD": 3, "algorithm___TruncatedSVD": "arpack", "clustering_choice": "KMeans", "dim_reduction_choice": "TruncatedSVD", "random_state___TruncatedSVD": 7}, -0.34053382866330956], [{"random_state___KernelPCA": 2, "n_components___KernelPCA": 2, "covariance_type___GaussianMixture": "tied", "n_components___GaussianMixture": 5, "clustering_choice": "GaussianMixture", "random_state___GaussianMixture": 8, "init_params___GaussianMixture": "kmeans", "kernel___KernelPCA": "sigmoid", "dim_reduction_choice": "KernelPCA"}, -0.34046860100705706], [{"n_clusters___KMeans": 13, "n_components___TruncatedSVD": 4, "algorithm___TruncatedSVD": "randomized", "clustering_choice": "KMeans", "dim_reduction_choice": "TruncatedSVD", "random_state___TruncatedSVD": 1}, -0.3399656213793051], [{"n_components___PCA": 3, "clustering_choice": "MiniBatchKMeans", "batch_size___MiniBatchKMeans": 175, "n_clusters___MiniBatchKMeans": 29, "random_state___PCA": 8, "dim_reduction_choice": "PCA", "svd_solver___PCA": "full"}, -0.3335613774566895], [{"random_state___KernelPCA": 7, "n_components___KernelPCA": 6, "min_samples___OPTICS": 861, "cluster_method___OPTICS": "xi", "clustering_choice": "OPTICS", "metric___OPTICS": "l1", "kernel___KernelPCA": "linear", "dim_reduction_choice": "KernelPCA"}, -0.3330527103294032], [{"affinity___AgglomerativeClustering": "l1", "batch_size___IncrementalPCA": 140, "linkage___AgglomerativeClustering": "average", "n_components___IncrementalPCA": 3, "clustering_choice": "AgglomerativeClustering", "n_clusters___AgglomerativeClustering": 8, "dim_reduction_choice": "IncrementalPCA"}, -0.33230251016853307], [{"whiten___PCA": true, "n_components___PCA": 3, "clustering_choice": "MiniBatchKMeans", "batch_size___MiniBatchKMeans": 520, "n_clusters___MiniBatchKMeans": 7, "random_state___PCA": 3, "dim_reduction_choice": "PCA", "random_state___MiniBatchKMeans": 9, "svd_solver___PCA": "full"}, -0.3300338567660386], [{"batch_size___IncrementalPCA": 866, "metric___OPTICS": "euclidean", "min_samples___OPTICS": 262, "clustering_choice": "OPTICS", "cluster_method___OPTICS": "dbscan", "n_components___IncrementalPCA": 2, "dim_reduction_choice": "IncrementalPCA"}, -0.3299748510630676], [{"whiten___PCA": true, "n_components___PCA": 3, "n_clusters___KMeans": 22, "clustering_choice": "KMeans", "random_state___PCA": 8, "dim_reduction_choice": "PCA", "svd_solver___PCA": "full"}, -0.32585441940529836], [{"n_components___PCA": 3, "clustering_choice": "MiniBatchKMeans", "batch_size___MiniBatchKMeans": 452, "n_clusters___MiniBatchKMeans": 7, "random_state___PCA": 3, "dim_reduction_choice": "PCA", "random_state___MiniBatchKMeans": 6, "svd_solver___PCA": "auto"}, -0.3240357296639891], [{"whiten___PCA": true, "n_components___PCA": 3, "clustering_choice": "MiniBatchKMeans", "batch_size___MiniBatchKMeans": 522, "n_clusters___MiniBatchKMeans": 27, "random_state___PCA": 1, "dim_reduction_choice": "PCA", "random_state___MiniBatchKMeans": 9, "svd_solver___PCA": "arpack"}, -0.3228951123252777], [{"affinity___AgglomerativeClustering": "l1", "whiten___FastICA": true, "n_components___FastICA": 3, "fun___FastICA": "cube", "linkage___AgglomerativeClustering": "complete", "clustering_choice": "AgglomerativeClustering", "n_clusters___AgglomerativeClustering": 8, "dim_reduction_choice": "FastICA", "algorithm___FastICA": "parallel", "random_state___FastICA": 9}, -0.32240981259503554], [{"whiten___PCA": true, "n_components___PCA": 3, "clustering_choice": "MiniBatchKMeans", "batch_size___MiniBatchKMeans": 140, "n_clusters___MiniBatchKMeans": 20, "random_state___PCA": 4, "dim_reduction_choice": "PCA", "svd_solver___PCA": "auto"}, -0.3211494520959611], [{"batch_size___IncrementalPCA": 908, "whiten___IncrementalPCA": true, "affinity___AffinityPropagation": "euclidean", "n_components___IncrementalPCA": 3, "clustering_choice": "AffinityPropagation", "dim_reduction_choice": "IncrementalPCA", "damping___AffinityPropagation": 0.8988541821915593}, -0.31712331336682725], [{"batch_size___IncrementalPCA": 800, "n_clusters___Birch": 9, "branching_factor___Birch": 639, "n_components___IncrementalPCA": 3, "clustering_choice": "Birch", "dim_reduction_choice": "IncrementalPCA"}, -0.3010269207311514], [{"random_state___KernelPCA": 4, "n_components___KernelPCA": 3, "covariance_type___GaussianMixture": "tied", "n_components___GaussianMixture": 5, "clustering_choice": "GaussianMixture", "random_state___GaussianMixture": 1, "init_params___GaussianMixture": "kmeans", "kernel___KernelPCA": "linear", "dim_reduction_choice": "KernelPCA"}, -0.29685768020609726], [{"n_components___TruncatedSVD": 3, "algorithm___TruncatedSVD": "arpack", "covariance_type___GaussianMixture": "tied", "n_components___GaussianMixture": 7, "clustering_choice": "GaussianMixture", "random_state___GaussianMixture": 7, "init_params___GaussianMixture": "kmeans", "dim_reduction_choice": "TruncatedSVD", "random_state___TruncatedSVD": 1}, -0.2897688431761252], [{"whiten___PCA": true, "n_components___PCA": 3, "n_clusters___Birch": 18, "branching_factor___Birch": 662, "clustering_choice": "Birch", "random_state___PCA": 6, "dim_reduction_choice": "PCA", "svd_solver___PCA": "randomized"}, -0.2793320921760606], [{"whiten___FastICA": true, "n_components___FastICA": 3, "fun___FastICA": "logcosh", "affinity___AffinityPropagation": "euclidean", "clustering_choice": "AffinityPropagation", "dim_reduction_choice": "FastICA", "damping___AffinityPropagation": 0.9613428432882517, "random_state___FastICA": 9, "algorithm___FastICA": "deflation"}, -0.2786275997808197], [{"affinity___AgglomerativeClustering": "l1", "n_components___PCA": 3, "linkage___AgglomerativeClustering": "complete", "clustering_choice": "AgglomerativeClustering", "n_clusters___AgglomerativeClustering": 29, "random_state___PCA": 5, "dim_reduction_choice": "PCA", "svd_solver___PCA": "arpack"}, -0.27780653077853146], [{"n_components___PCA": 3, "n_clusters___Birch": 20, "branching_factor___Birch": 295, "clustering_choice": "Birch", "random_state___PCA": 3, "dim_reduction_choice": "PCA", "svd_solver___PCA": "arpack"}, -0.27545469944286227], [{"whiten___PCA": true, "n_components___PCA": 3, "n_clusters___Birch": 17, "branching_factor___Birch": 704, "clustering_choice": "Birch", "random_state___PCA": 9, "dim_reduction_choice": "PCA", "svd_solver___PCA": "randomized"}, -0.2679800632574878], [{"n_components___KernelPCA": 8, "random_state___MiniBatchKMeans": 7, "n_clusters___MiniBatchKMeans": 28, "batch_size___MiniBatchKMeans": 158, "clustering_choice": "MiniBatchKMeans", "kernel___KernelPCA": "sigmoid", "dim_reduction_choice": "KernelPCA"}, -0.25123613013818513], [{"whiten___PCA": true, "eigen_solver___SpectralClustering": "arpack", "n_components___PCA": 2, "svd_solver___PCA": "auto", "assign_labels___SpectralClustering": "discretize", "clustering_choice": "SpectralClustering", "random_state___PCA": 5, "dim_reduction_choice": "PCA", "n_clusters___SpectralClustering": 19, "affinity___SpectralClustering": "poly"}, -0.24889335248916672], [{"whiten___FastICA": true, "n_components___FastICA": 3, "fun___FastICA": "logcosh", "covariance_type___GaussianMixture": "tied", "n_components___GaussianMixture": 8, "clustering_choice": "GaussianMixture", "random_state___GaussianMixture": 5, "init_params___GaussianMixture": "kmeans", "dim_reduction_choice": "FastICA", "algorithm___FastICA": "parallel", "random_state___FastICA": 4}, -0.23057594287279945], [{"batch_size___IncrementalPCA": 280, "whiten___IncrementalPCA": true, "init_params___GaussianMixture": "random", "covariance_type___GaussianMixture": "diag", "n_components___GaussianMixture": 5, "clustering_choice": "GaussianMixture", "random_state___GaussianMixture": 9, "n_components___IncrementalPCA": 3, "dim_reduction_choice": "IncrementalPCA", "warm_start___GaussianMixture": true}, -0.2176925255073636], [{"batch_size___IncrementalPCA": 906, "whiten___IncrementalPCA": true, "init_params___GaussianMixture": "kmeans", "covariance_type___GaussianMixture": "full", "n_components___GaussianMixture": 19, "clustering_choice": "GaussianMixture", "random_state___GaussianMixture": 1, "n_components___IncrementalPCA": 3, "dim_reduction_choice": "IncrementalPCA"}, -0.19963892397178712], [{"whiten___PCA": true, "eigen_solver___SpectralClustering": "arpack", "n_components___PCA": 3, "svd_solver___PCA": "arpack", "assign_labels___SpectralClustering": "kmeans", "clustering_choice": "SpectralClustering", "random_state___PCA": 6, "dim_reduction_choice": "PCA", "n_clusters___SpectralClustering": 18, "affinity___SpectralClustering": "poly"}, -0.17691150463105154], [{"affinity___AgglomerativeClustering": "cosine", "batch_size___IncrementalPCA": 818, "whiten___IncrementalPCA": true, "linkage___AgglomerativeClustering": "average", "n_components___IncrementalPCA": 3, "clustering_choice": "AgglomerativeClustering", "n_clusters___AgglomerativeClustering": 25, "dim_reduction_choice": "IncrementalPCA"}, -0.15342706014957003], [{"affinity___AgglomerativeClustering": "euclidean", "whiten___FastICA": true, "n_components___FastICA": 2, "fun___FastICA": "cube", "linkage___AgglomerativeClustering": "single", "clustering_choice": "AgglomerativeClustering", "n_clusters___AgglomerativeClustering": 11, "dim_reduction_choice": "FastICA", "algorithm___FastICA": "deflation", "random_state___FastICA": 8}, -0.13713743265490883], [{"whiten___FastICA": true, "eigen_solver___SpectralClustering": "arpack", "n_clusters___SpectralClustering": 6, "fun___FastICA": "exp", "assign_labels___SpectralClustering": "kmeans", "clustering_choice": "SpectralClustering", "algorithm___FastICA": "deflation", "dim_reduction_choice": "FastICA", "n_components___FastICA": 2, "random_state___FastICA": 1, "affinity___SpectralClustering": "sigmoid"}, -0.13009790573047636], [{"batch_size___IncrementalPCA": 290, "whiten___IncrementalPCA": true, "init_params___GaussianMixture": "random", "covariance_type___GaussianMixture": "full", "n_components___GaussianMixture": 6, "clustering_choice": "GaussianMixture", "random_state___GaussianMixture": 9, "n_components___IncrementalPCA": 3, "dim_reduction_choice": "IncrementalPCA", "warm_start___GaussianMixture": true}, -0.11687297548381506], [{"batch_size___IncrementalPCA": 322, "init_params___GaussianMixture": "random", "covariance_type___GaussianMixture": "tied", "n_components___GaussianMixture": 30, "clustering_choice": "GaussianMixture", "random_state___GaussianMixture": 6, "n_components___IncrementalPCA": 2, "dim_reduction_choice": "IncrementalPCA"}, -0.10520169519095109], [{"random_state___KernelPCA": 2, "n_components___KernelPCA": 5, "min_samples___OPTICS": 572, "cluster_method___OPTICS": "dbscan", "clustering_choice": "OPTICS", "metric___OPTICS": "l2", "kernel___KernelPCA": "cosine", "dim_reduction_choice": "KernelPCA"}, -0.09242108625845426], [{"batch_size___IncrementalPCA": 763, "whiten___IncrementalPCA": true, "init_params___GaussianMixture": "random", "covariance_type___GaussianMixture": "full", "n_components___GaussianMixture": 26, "clustering_choice": "GaussianMixture", "random_state___GaussianMixture": 1, "n_components___IncrementalPCA": 2, "dim_reduction_choice": "IncrementalPCA"}, -0.0825342018279604], [{"affinity___AgglomerativeClustering": "euclidean", "linkage___AgglomerativeClustering": "single", "early_exaggeration___TSNE": 15.615876239354236, "clustering_choice": "AgglomerativeClustering", "n_clusters___AgglomerativeClustering": 24, "dim_reduction_choice": "TSNE", "n_components___TSNE": 2, "perplexity___TSNE": 206.2028721981697}, -0.027536513283848763], [{"eigen_solver___SpectralClustering": "arpack", "n_clusters___SpectralClustering": 15, "random_state___TSNE": 5, "assign_labels___SpectralClustering": "discretize", "early_exaggeration___TSNE": 6.471918049681238, "clustering_choice": "SpectralClustering", "n_components___TSNE": 2, "affinity___SpectralClustering": "sigmoid", "dim_reduction_choice": "TSNE", "perplexity___TSNE": 196.53183093340755}, -0.019834008067846298], [{"affinity___AgglomerativeClustering": "manhattan", "n_components___PCA": 2, "linkage___AgglomerativeClustering": "single", "clustering_choice": "AgglomerativeClustering", "n_clusters___AgglomerativeClustering": 22, "random_state___PCA": 6, "dim_reduction_choice": "PCA", "svd_solver___PCA": "full"}, 0.023102547912838917], [{"random_state___KernelPCA": 3, "n_components___KernelPCA": 9, "covariance_type___GaussianMixture": "tied", "n_components___GaussianMixture": 27, "clustering_choice": "GaussianMixture", "random_state___GaussianMixture": 4, "init_params___GaussianMixture": "random", "kernel___KernelPCA": "linear", "warm_start___GaussianMixture": true, "dim_reduction_choice": "KernelPCA"}, 0.1662539796637227], [{"whiten___PCA": true, "min_samples___DBSCAN": 91, "n_components___PCA": 2, "eps___DBSCAN": 2.3141383093730274, "clustering_choice": "DBSCAN", "random_state___PCA": 1, "dim_reduction_choice": "PCA", "svd_solver___PCA": "randomized"}, Infinity], [{"n_components___PCA": 2, "bandwidth___MeanShift": 13.078848851456442, "clustering_choice": "MeanShift", "random_state___PCA": 3, "dim_reduction_choice": "PCA", "svd_solver___PCA": "arpack"}, Infinity], [{"min_samples___DBSCAN": 45, "n_components___PCA": 2, "eps___DBSCAN": 4.67564174908492, "clustering_choice": "DBSCAN", "random_state___PCA": 9, "dim_reduction_choice": "PCA", "svd_solver___PCA": "full"}, Infinity], [{"min_samples___DBSCAN": 93, "early_exaggeration___TSNE": 8.492703557924255, "eps___DBSCAN": 1.2599588232384924, "random_state___TSNE": 4, "clustering_choice": "DBSCAN", "n_components___TSNE": 2, "dim_reduction_choice": "TSNE", "perplexity___TSNE": 158.66434600673003}, Infinity], [{"whiten___PCA": true, "bin_seeding___MeanShift": true, "n_components___PCA": 3, "bandwidth___MeanShift": 30.269352216250727, "clustering_choice": "MeanShift", "random_state___PCA": 9, "dim_reduction_choice": "PCA", "svd_solver___PCA": "randomized"}, Infinity], [{"random_state___TSNE": 1, "early_exaggeration___TSNE": 12.0, "covariance_type___GaussianMixture": "spherical", "n_components___GaussianMixture": 1, "clustering_choice": "GaussianMixture", "random_state___GaussianMixture": 1, "init_params___GaussianMixture": "kmeans", "n_components___TSNE": 2, "warm_start___GaussianMixture": true, "dim_reduction_choice": "TSNE", "perplexity___TSNE": 30.0}, Infinity], [{"n_components___PCA": 3, "bandwidth___MeanShift": 18.047180831641054, "clustering_choice": "MeanShift", "random_state___PCA": 7, "dim_reduction_choice": "PCA", "svd_solver___PCA": "randomized"}, Infinity], [{"min_samples___DBSCAN": 11, "n_components___KernelPCA": 2, "eps___DBSCAN": 1.943190255411418, "clustering_choice": "DBSCAN", "kernel___KernelPCA": "rbf", "dim_reduction_choice": "KernelPCA"}, Infinity], [{"n_clusters___KMeans": 1, "early_exaggeration___TSNE": 12.701826662279423, "clustering_choice": "KMeans", "n_components___TSNE": 2, "dim_reduction_choice": "TSNE", "perplexity___TSNE": 36.607883908282716}, Infinity], [{"eigen_solver___SpectralClustering": "arpack", "n_components___PCA": 3, "svd_solver___PCA": "full", "assign_labels___SpectralClustering": "discretize", "clustering_choice": "SpectralClustering", "random_state___PCA": 2, "dim_reduction_choice": "PCA", "n_clusters___SpectralClustering": 1, "affinity___SpectralClustering": "poly"}, Infinity], [{"n_components___PCA": 3, "n_clusters___Birch": 1, "branching_factor___Birch": 438, "clustering_choice": "Birch", "random_state___PCA": 8, "dim_reduction_choice": "PCA", "svd_solver___PCA": "randomized"}, Infinity], [{"whiten___FastICA": true, "n_components___FastICA": 2, "fun___FastICA": "exp", "bandwidth___MeanShift": 7.391185952554738, "clustering_choice": "MeanShift", "dim_reduction_choice": "FastICA", "algorithm___FastICA": "parallel", "random_state___FastICA": 5}, Infinity], [{"whiten___PCA": true, "n_components___PCA": 3, "bandwidth___MeanShift": 4.435485605092141, "clustering_choice": "MeanShift", "random_state___PCA": 9, "dim_reduction_choice": "PCA", "svd_solver___PCA": "full"}, Infinity], [{"min_samples___DBSCAN": 59, "n_components___KernelPCA": 8, "eps___DBSCAN": 1.0437500264439783, "random_state___KernelPCA": 8, "clustering_choice": "DBSCAN", "kernel___KernelPCA": "sigmoid", "dim_reduction_choice": "KernelPCA"}, Infinity], [{"whiten___PCA": true, "bin_seeding___MeanShift": true, "n_components___PCA": 3, "bandwidth___MeanShift": 18.881222012729236, "clustering_choice": "MeanShift", "random_state___PCA": 8, "dim_reduction_choice": "PCA", "svd_solver___PCA": "full"}, Infinity], [{"early_exaggeration___TSNE": 7.669208257565115, "min_samples___OPTICS": 148, "clustering_choice": "OPTICS", "random_state___TSNE": 7, "cluster_method___OPTICS": "xi", "metric___OPTICS": "manhattan", "n_components___TSNE": 2, "dim_reduction_choice": "TSNE", "perplexity___TSNE": 93.36892214170844}, Infinity], [{"whiten___PCA": true, "eigen_solver___SpectralClustering": "arpack", "n_components___PCA": 3, "svd_solver___PCA": "auto", "assign_labels___SpectralClustering": "discretize", "clustering_choice": "SpectralClustering", "random_state___PCA": 9, "dim_reduction_choice": "PCA", "n_clusters___SpectralClustering": 1, "affinity___SpectralClustering": "laplacian"}, Infinity], [{"batch_size___IncrementalPCA": 26, "n_clusters___Birch": 1, "branching_factor___Birch": 235, "n_components___IncrementalPCA": 3, "clustering_choice": "Birch", "dim_reduction_choice": "IncrementalPCA"}, Infinity], [{"min_samples___DBSCAN": 49, "whiten___IncrementalPCA": true, "eps___DBSCAN": 2.4246007104191185, "batch_size___IncrementalPCA": 27, "clustering_choice": "DBSCAN", "n_components___IncrementalPCA": 2, "dim_reduction_choice": "IncrementalPCA"}, Infinity], [{"whiten___PCA": true, "n_components___PCA": 3, "metric___OPTICS": "l1", "min_samples___OPTICS": 333, "clustering_choice": "OPTICS", "cluster_method___OPTICS": "dbscan", "random_state___PCA": 6, "dim_reduction_choice": "PCA", "svd_solver___PCA": "full"}, Infinity], [{"batch_size___IncrementalPCA": 544, "n_clusters___SpectralClustering": 1, "assign_labels___SpectralClustering": "discretize", "eigen_solver___SpectralClustering": "arpack", "clustering_choice": "SpectralClustering", "n_components___IncrementalPCA": 2, "dim_reduction_choice": "IncrementalPCA", "whiten___IncrementalPCA": true, "affinity___SpectralClustering": "laplacian"}, Infinity], [{"n_clusters___KMeans": 1, "early_exaggeration___TSNE": 12.18551141477279, "clustering_choice": "KMeans", "n_components___TSNE": 2, "dim_reduction_choice": "TSNE", "perplexity___TSNE": 27.203424263460324}, Infinity], [{"n_components___FastICA": 2, "n_clusters___Birch": 21, "branching_factor___Birch": 749, "fun___FastICA": "exp", "clustering_choice": "Birch", "dim_reduction_choice": "FastICA", "algorithm___FastICA": "parallel", "random_state___FastICA": 2}, Infinity], [{"clustering_choice": "MeanShift", "batch_size___IncrementalPCA": 768, "dim_reduction_choice": "IncrementalPCA", "bandwidth___MeanShift": 21.795025272966146, "n_components___IncrementalPCA": 2}, Infinity], [{"early_exaggeration___TSNE": 13.738778564728962, "n_clusters___KMeans": 1, "random_state___TSNE": 2, "clustering_choice": "KMeans", "n_components___TSNE": 2, "dim_reduction_choice": "TSNE", "perplexity___TSNE": 22.186949133735688}, Infinity], [{"whiten___PCA": true, "n_components___PCA": 2, "bandwidth___MeanShift": 12.818232014493935, "clustering_choice": "MeanShift", "random_state___PCA": 4, "dim_reduction_choice": "PCA", "svd_solver___PCA": "arpack"}, Infinity]]}
